oci_bucket/__init__.py
oci_bucket/oci_bucket.py
oci_bucket-1.0.3.dist-info/METADATA
oci_bucket-1.0.3.dist-info/WHEEL
oci_bucket-1.0.3.dist-info/top_level.txt
oci_bucket-1.0.3.dist-info/RECORD
