Metadata-Version: 2.4
Name: oci_bucket
Version: 1.0.3
Summary: Package for easy Oci Buckets management in python.
Project-URL: Homepage, https://github.com/dsantiago/oci_bucket
Project-URL: Repository, https://github.com/dsantiago/oci_bucket
Requires-Python: >=3.11
Requires-Dist: oci>=2.153.0
